modifiable_items_dictionary/__init__.py
modifiable_items_dictionary/modifiable_items_attribute_dictionary.py
modifiable_items_dictionary/modifiable_items_dictionary.py
modifiable_items_dictionary/py.typed
modifiable_items_dictionary-3.0.2.dist-info/LICENSE
modifiable_items_dictionary-3.0.2.dist-info/METADATA
modifiable_items_dictionary-3.0.2.dist-info/WHEEL
modifiable_items_dictionary-3.0.2.dist-info/top_level.txt
modifiable_items_dictionary-3.0.2.dist-info/RECORD
