Metadata-Version: 2.1
Name: modifiable-items-dictionary
Version: 3.0.2
Summary: Typed and Tested Modifiable Items Dict and ModifiableItemsAttrDict which allow keys and values to be modified at run time. ModifiableItemsAttrDict additionally provides attribute-style access to dictionary items.
Home-page: https://github.com/tybruno/modifiable-items-dictionary
Author: Tyler Bruno
License: MIT
Keywords: python dict attribute dictionary attrdict mapping key-mangling value-mangling
Classifier: License :: OSI Approved :: MIT License
Classifier: Operating System :: POSIX :: Linux
Classifier: Operating System :: MacOS
Classifier: Programming Language :: Python :: 3.6
Classifier: Programming Language :: Python :: 3.7
Classifier: Programming Language :: Python :: 3.8
Classifier: Programming Language :: Python :: 3.9
Classifier: Programming Language :: Python :: 3.10
Classifier: Programming Language :: Python :: 3.11
Classifier: Programming Language :: Python :: 3 :: Only
Classifier: Topic :: Software Development :: Libraries :: Python Modules
Requires-Python: >=3.6
License-File: LICENSE
